pysciiart/coordinates.py
pysciiart/graph.py
pysciiart/graph_layer.py
pysciiart/graph_solver.py
pysciiart/raster.py
pysciiart/widget.py
pysciiart-0.3.0.dist-info/METADATA
pysciiart-0.3.0.dist-info/WHEEL
pysciiart-0.3.0.dist-info/RECORD
