Metadata-Version: 2.3
Name: pysciiart
Version: 0.3.0
Summary: A set of python libraries used to generate ASCII art from high level data structures.
License: MIT
Author: Yannick Kirschhoffer
Author-email: alcibiade@alcibiade.org
Maintainer: Yannick Kirschhoffer
Maintainer-email: alcibiade@alcibiade.org
Requires-Python: >=3.7.0,<4.0.0
Classifier: Development Status :: 5 - Production/Stable
Classifier: Intended Audience :: Developers
Classifier: Intended Audience :: System Administrators
Classifier: License :: OSI Approved :: MIT License
Classifier: Programming Language :: Python :: 3
Classifier: Programming Language :: Python :: 3.7
Classifier: Programming Language :: Python :: 3.8
Classifier: Programming Language :: Python :: 3.9
Classifier: Programming Language :: Python :: 3.10
Classifier: Programming Language :: Python :: 3.11
Classifier: Programming Language :: Python :: 3.12
Classifier: Programming Language :: Python :: 3.13
Classifier: Topic :: System :: Systems Administration
Requires-Dist: termcolor (==1.1.0)
Project-URL: Repository, https://gitlab.com/alcibiade/pysciiart
